Metadata-Version: 2.1
Name: CherwellAPI
Version: 1.3.3
Summary: A Python library wrapper, abstracting the Cherwell REST API
Home-page: UNKNOWN
Author: Streamline Partners PTY Ltd
Author-email: david.graupner@streamlinepartners.com.au
License: UNKNOWN
Platform: UNKNOWN
Classifier: Programming Language :: Python :: 2.6
Classifier: Programming Language :: Python :: 2.7
Classifier: Programming Language :: Python :: 3.4
Classifier: Programming Language :: Python :: 3.5
Classifier: Programming Language :: Python :: 3.6
Classifier: Programming Language :: Python :: 3.7
Classifier: License :: OSI Approved :: MIT License
Classifier: Operating System :: OS Independent
